casatestutils/__init__.py
casatestutils/check.py
casatestutils/compare.py
casatestutils/component_to_test_map.json
casatestutils/extractcasascript.py
casatestutils/filltsys.py
casatestutils/listing.py
casatestutils/restfreqtool.py
casatestutils/runtest.py
casatestutils/selection_syntax.py
casatestutils/sparse_check.py
casatestutils/testhelper.py
casatestutils/weblog.py
casatestutils/xmlhelper.py
casatestutils/datahelpers/__init__.py
casatestutils/datahelpers/getTelescope.py
casatestutils/datahelpers/selectTaql.py
casatestutils/getantposalma_helpers/__init__.py
casatestutils/getantposalma_helpers/query1.json
casatestutils/getcalmodvla_helpers/__init__.py
casatestutils/getcalmodvla_helpers/query1.json
casatestutils/imagerhelpers/__init__.py
casatestutils/imagerhelpers/imagetesthelpers.py
casatestutils/stakeholder/StkUnitTest.py
casatestutils/stakeholder/__init__.py
casatestutils/stakeholder/almastktestutils.py
casatestutils-6.7.2.42.dist-info/licenses/LICENSE
testrunner/__init__.py
testrunner/atlassian_helper.py
testrunner/run.py
testrunner/shell_runner.py
testrunner/xunit.py
testrunner/xvfb_helper.py
casatestutils-6.7.2.42.dist-info/METADATA
casatestutils-6.7.2.42.dist-info/WHEEL
casatestutils-6.7.2.42.dist-info/top_level.txt
casatestutils-6.7.2.42.dist-info/RECORD
