Metadata-Version: 2.4
Name: casatestutils
Version: 6.7.2.42
Summary: Tools for use with casatest and testing
Home-page: https://open-bitbucket.nrao.edu/projects/CASA/repos/casa6/browse
Download-URL: https://casa.nrao.edu/download/
Author: A. Wells
Author-email: awells@nrao.edu
Classifier: Programming Language :: Python :: 3
Classifier: License :: OSI Approved :: MIT License
Classifier: Operating System :: OS Independent
Requires-Python: >=3.6
License-File: LICENSE
Requires-Dist: pytest
Dynamic: author
Dynamic: author-email
Dynamic: classifier
Dynamic: description
Dynamic: description-content-type
Dynamic: download-url
Dynamic: home-page
Dynamic: license-file
Dynamic: requires-dist
Dynamic: requires-python
Dynamic: summary
